mypackage/__init__.py
mypackage/mymodule.py
tests/__init__.py
tests/test_mymodule.py
new0325_package-0.1.0.dist-info/LICENSE
new0325_package-0.1.0.dist-info/METADATA
new0325_package-0.1.0.dist-info/WHEEL
new0325_package-0.1.0.dist-info/top_level.txt
new0325_package-0.1.0.dist-info/RECORD
